README.md
setup.py
src/sentry_dynamo/__init__.py
src/sentry_dynamo.egg-info/PKG-INFO
src/sentry_dynamo.egg-info/SOURCES.txt
src/sentry_dynamo.egg-info/dependency_links.txt
src/sentry_dynamo.egg-info/requires.txt
src/sentry_dynamo.egg-info/top_level.txt
src/sentry_dynamo/dynamo/__init__.py
src/sentry_dynamo/dynamo/nodestore/__init__.py
src/sentry_dynamo/dynamo/nodestore/backend.py