Metadata-Version: 1.0
Name: sentry-dynamo
Version: 0.1
Summary: A Sentry Dynamo NodeStorage library
Home-page: UNKNOWN
Author: Dusan Jovanovic
Author-email: dusan@flipboard.com
License: UNKNOWN
Platform: UNKNOWN
